pynipt/__init__.py
pynipt/config.py
pynipt/errors.py
pynipt/utils.py
pynipt/lib/__init__.py
pynipt/lib/bucket.py
pynipt/lib/interface.py
pynipt/lib/pipeline.py
pynipt/lib/plugin.py
pynipt/lib/processor.py
pynipt/scripts/__init__.py
pynipt/scripts/pynipt.py
PyNIPT-0.2.3.dist-info/METADATA
PyNIPT-0.2.3.dist-info/WHEEL
PyNIPT-0.2.3.dist-info/top_level.txt
PyNIPT-0.2.3.dist-info/RECORD
